n0ryb/__init__.py
n0ryb/courses.py
n0ryb/utils.py
n0ryb-0.5.1.dist-info/METADATA
n0ryb-0.5.1.dist-info/WHEEL
n0ryb-0.5.1.dist-info/top_level.txt
n0ryb-0.5.1.dist-info/RECORD
