Metadata-Version: 2.1
Name: n0ryb
Version: 0.5.1
Summary: Una prueba para consultar biblioteca de la academia hack4u
Home-page: https://hack4u.io
Author: NORYB Profesor: S4vitar
